drf_attachments/__init__.py
drf_attachments/admin.py
drf_attachments/apps.py
drf_attachments/config.py
drf_attachments/handlers.py
drf_attachments/storage.py
drf_attachments/utils.py
drf_attachments/migrations/0001_initial.py
drf_attachments/migrations/0002_attachment_object_id_types.py
drf_attachments/migrations/0003_alter_attachment_file.py
drf_attachments/migrations/__init__.py
drf_attachments/models/__init__.py
drf_attachments/models/fields.py
drf_attachments/models/managers.py
drf_attachments/models/models.py
drf_attachments/models/querysets.py
drf_attachments/rest/__init__.py
drf_attachments/rest/fields.py
drf_attachments/rest/renderers.py
drf_attachments/rest/serializers.py
drf_attachments/rest/views.py
drf_attachments-0.4.2.dist-info/LICENSE
drf_attachments-0.4.2.dist-info/METADATA
drf_attachments-0.4.2.dist-info/WHEEL
drf_attachments-0.4.2.dist-info/top_level.txt
drf_attachments-0.4.2.dist-info/RECORD
