Metadata-Version: 2.1
Name: drf-attachments
Version: 0.4.2
Summary: A django module to manage any model's file up-/downloads by relating an Attachment model to it.
Home-page: https://github.com/anexia/drf-attachments
Author: Alexandra Bruckner
Author-email: abruckner@anexia-it.com
License: MIT License
Classifier: Development Status :: 5 - Production/Stable
Classifier: Framework :: Django
Classifier: Framework :: Django :: 3.2
Classifier: Intended Audience :: Developers
Classifier: License :: OSI Approved :: MIT License
Classifier: Operating System :: OS Independent
Classifier: Programming Language :: Python
Classifier: Programming Language :: Python :: 3
Classifier: Programming Language :: Python :: 3.7
Classifier: Programming Language :: Python :: 3.8
Classifier: Programming Language :: Python :: 3.9
Classifier: Programming Language :: Python :: 3.10
License-File: LICENSE
Requires-Dist: python-magic>=0.4.18
Requires-Dist: rest-framework-generic-relations>=2.0.0
Requires-Dist: content-disposition>=1.1.0
